reelity/__init__.py
reelity/module.MD
reelity/module.s.HTML
reelity/names.s.HTML
reelity/procedure.proc.py
reelity/__book/codesweeper--ai-generated-8311435_1920.jpg
reelity/__book/codesweeper--ai-generated-8311446_1920.jpg
reelity/__book/codesweeper--ai-generated-8311450_1920.jpg
reelity/__license/license.s.HTML
reelity/__license/options/gpl-3.0-standalone.html
reelity/_clique/__init__.py
reelity/_clique/group/__init__.py
reelity/_status/__init__.py
reelity/_status/status.proc.py
reelity/_status/_stories/story_instrument_1/status_1.py
reelity/instrument/__init__.py
reelity/instrument/module--names.s.HTML
reelity/instrument/start.proc.py
reelity/instrument/__agenda/agenda.s.HTML
reelity/instrument/__book/TheDigitalArtist--ai-generated-8228359_1920.jpg
reelity/instrument/__book/TheDigitalArtist--ai-generated-8228360_1920.jpg
reelity/instrument/__book/dlsdkcgl--hidden-8315722_1920.jpg
reelity/instrument/__book/_hardware/hardware.s.HTML
reelity/instrument/__book/_hardware/ISO/ISO_lab.s.HTML
reelity/instrument/__book/_hardware/ISO/ISO_lab_2.s.HTML
reelity/instrument/__book/_hardware/ISO/write_ISO_to_drive.py
reelity/instrument/__book/_hardware/docker/docker.s.HTML
reelity/instrument/__book/_hardware/docker/essential_installations.s.HTML
reelity/instrument/__book/_hardware/docker/compose/compose.s.HTML
reelity/instrument/__book/_hardware/docker/containers/containers.s.HTML
reelity/instrument/__book/_hardware/docker/containers/installations.s.HTML
reelity/instrument/__book/_hardware/docker/images/images.s.HTML
reelity/instrument/_status/status_1.py
reelity/instrument/climate/__init__.py
reelity/instrument/clique/__init__.py
reelity/instrument/frontend/index.html
reelity/instrument/frontend/assets/feel-5eb29397.js
reelity/instrument/frontend/assets/futon-32fc3a76.js
reelity/instrument/frontend/assets/index-a898c826.js
reelity/instrument/frontend/assets/index-e839d257.css
reelity/instrument/frontend/assets/perform-33c82eac.js
reelity-1.0.10.dist-info/METADATA
reelity-1.0.10.dist-info/WHEEL
reelity-1.0.10.dist-info/entry_points.txt
reelity-1.0.10.dist-info/top_level.txt
reelity-1.0.10.dist-info/RECORD
