Metadata-Version: 2.1
Name: reelity
Version: 1.0.10
Summary: The dreams that found there way to a canvas.
License: GPL 3.0 + MongoDB SSPL
Keywords: custom support required
Requires-Dist: bracelet
Requires-Dist: carbonado
Requires-Dist: ships
Requires-Dist: asn1crypto
Requires-Dist: aztec-code-generator
Requires-Dist: click
Requires-Dist: ecdsa
Requires-Dist: ECPy
Requires-Dist: flask
Requires-Dist: flask-cors
Requires-Dist: flask-openapi3
Requires-Dist: rich
Requires-Dist: selenium
Requires-Dist: textual
Requires-Dist: websockets
Requires-Dist: pycryptodome
Requires-Dist: PyOpenSSL
Requires-Dist: pymongo
Requires-Dist: pyzbar
Requires-Dist: qrcode
